canprog/__init__.py
canprog/file.py
canprog/logger.py
canprog/main.py
canprog/protocols/__init__.py
canprog/protocols/abstract.py
canprog/protocols/stm32.py
canprog/tests/__init__.py
canprog-0.1.2.dist-info/DESCRIPTION.rst
canprog-0.1.2.dist-info/METADATA
canprog-0.1.2.dist-info/RECORD
canprog-0.1.2.dist-info/WHEEL
canprog-0.1.2.dist-info/entry_points.txt
canprog-0.1.2.dist-info/metadata.json
canprog-0.1.2.dist-info/top_level.txt
