Metadata-Version: 2.0
Name: canprog
Version: 0.1.2
Summary: Command-line tool to flashing devices by CAN-BUS.
Home-page: https://github.com/marcinbor85/CAN-Prog
Author: Marcin Borowicz
Author-email: marcinbor85@gmail.com
License: MIT
Keywords: bootloader socketcan can stm32
Platform: UNKNOWN
Classifier: Development Status :: 3 - Alpha
Classifier: License :: OSI Approved :: MIT License
Classifier: Intended Audience :: Telecommunications Industry
Classifier: Environment :: Console
Classifier: Natural Language :: English
Classifier: Operating System :: POSIX :: Linux
Classifier: Programming Language :: Python :: 3.6
Classifier: Topic :: Scientific/Engineering :: Interface Engine/Protocol Translator
Classifier: Topic :: Software Development :: Embedded Systems
Requires-Dist: intelhex
Requires-Dist: python-can
